{
 "actions": [],
 "allow_rename": 1,
 "creation": "2024-02-25 15:30:56.378578",
 "doctype": "DocType",
 "editable_grid": 1,
 "engine": "InnoDB",
 "field_order": [
  "description",
  "department",
  "user",
  "section_break_3rfl"
 ],
 "fields": [
  {
   "fieldname": "section_break_3rfl",
   "fieldtype": "Section Break"
  },
  {
   "fieldname": "description",
   "fieldtype": "Small Text",
   "label": "Description "
  },
  {
   "fieldname": "department",
   "fieldtype": "Link",
   "label": "Department",
   "options": "Department"
  },
  {
   "fieldname": "user",
   "fieldtype": "Link",
   "label": "User",
   "options": "User"
  }
 ],
 "index_web_pages_for_search": 1,
 "istable": 1,
 "links": [],
 "modified": "2024-02-25 15:32:16.763820",
 "modified_by": "Administrator",
 "module": "Ecs Microfinance",
 "name": "Preparation Table",
 "owner": "Administrator",
 "permissions": [],
 "sort_field": "modified",
 "sort_order": "DESC",
 "states": []
}